[{"_id": "6580b3e31ebc4f1b43752b8d", "regnum": 261428, "snils": "12361805533", "applications": [{"total_mark": 97, "edu_doc_original": true, "achievs": 10, "status_epgu": "", "competition": "Основные места", "program": "Инженерия искусственного интеллекта", "priority": 1, "speciality": "09.04.01 Информатика и вычислительная техника", "is_without_tests": false, "familirization": "Очная", "avgm": 0.0, "institute": "ИРИТ-РТФ", "compensation": "контрактная основа", "status": "К зачислению", "marks": {"Экзамен 09.04.01;09.04.02": {"mark": 87, "case": "КТ"}}}, {"total_mark": 97, "edu_doc_original": true, "achievs": 10, "status_epgu": "", "competition": "Основные места", "program": "Инженерия машинного обучения", "priority": 2, "speciality": "09.04.01 Информатика и вычислительная техника", "is_without_tests": false, "familirization": "Очная", "avgm": 0.0, "institute": "ИРИТ-РТФ", "compensation": "контрактная основа", "status": "К зачислению", "marks": {"Экзамен 09.04.01;09.04.02": {"mark": 87, "case": "КТ"}}}, {"total_mark": 97, "edu_doc_original": true, "achievs": 10, "status_epgu": "", "competition": "Основные места", "program": "Прикладной анализ данных", "priority": 3, "speciality": "09.04.02 Информационные системы и технологии", "is_without_tests": false, "familirization": "Очная", "avgm": 0.0, "institute": "ИРИТ-РТФ", "compensation": "контрактная основа", "status": "К зачислению", "marks": {"Экзамен 09.04.01;09.04.02": {"mark": 87, "case": "КТ"}}}, {"total_mark": 97, "edu_doc_original": true, "achievs": 10, "status_epgu": "", "competition": "Основные места", "program": "Инженерия искусственного интеллекта", "priority": 1, "speciality": "09.04.01 Информатика и вычислительная техника", "is_without_tests": false, "familirization": "Очная", "avgm": 0.0, "institute": "ИРИТ-РТФ", "compensation": "бюджетная основа", "status": "К зачислению", "marks": {"Экзамен 09.04.01;09.04.02": {"mark": 87, "case": "КТ"}}}, {"total_mark": 97, "edu_doc_original": true, "achievs": 10, "status_epgu": "", "competition": "Основные места", "program": "Прикладной анализ данных", "priority": 2, "speciality": "09.04.02 Информационные системы и технологии", "is_without_tests": false, "familirization": "Очная", "avgm": 0.0, "institute": "ИРИТ-РТФ", "compensation": "бюджетная основа", "status": "К зачислению", "marks": {"Экзамен 09.04.01;09.04.02": {"mark": 87, "case": "КТ"}}}]}, {"_id": "6580b3e31ebc4f1b43752ba2", "regnum": 261449, "snils": "18763913925", "applications": [{"total_mark": 211, "edu_doc_original": true, "achievs": 0, "status_epgu": "", "competition": "Основные места", "program": "Безопасность компьютерных систем", "priority": 2, "speciality": "10.03.01 Информационная безопасность", "is_without_tests": false, "familirization": "Очно-заочная", "avgm": 0.0, "institute": "ИРИТ-РТФ", "compensation": "контрактная основа", "status": "В приказе", "marks": {"ОМА": {"mark": 50, "case": "КТ"}, "ИСиТ": {"mark": 82, "case": "КТ"}, "РЯ": {"mark": 64, "case": "КТ"}}}, {"total_mark": 211, "edu_doc_original": true, "achievs": 0, "status_epgu": "", "competition": "Основные места", "program": "Безопасность компьютерных систем", "priority": 1, "speciality": "10.03.01 Информационная безопасность", "is_without_tests": false, "familirization": "Очная", "avgm": 0.0, "institute": "ИРИТ-РТФ", "compensation": "контрактная основа", "status": "К зачислению", "marks": {"ОМА": {"mark": 50, "case": "КТ"}, "ИСиТ": {"mark": 82, "case": "КТ"}, "РЯ": {"mark": 64, "case": "КТ"}}}, {"total_mark": 211, "edu_doc_original": true, "achievs": 0, "status_epgu": "", "competition": "Основные места", "program": "Информационные системы и технологии", "priority": 3, "speciality": "09.03.02 Информационные системы и технологии", "is_without_tests": false, "familirization": "Очная", "avgm": 0.0, "institute": "ИНМТ", "compensation": "контрактная основа", "status": "К зачислению", "marks": {"ОМА": {"mark": 50, "case": "КТ"}, "ИСиТ": {"mark": 82, "case": "КТ"}, "РЯ": {"mark": 64, "case": "КТ"}}}, {"total_mark": 211, "edu_doc_original": true, "achievs": 0, "status_epgu": "", "competition": "Основные места", "program": "Информатика и вычислительная техника", "priority": 5, "speciality": "09.03.01 Информатика и вычислительная техника", "is_without_tests": false, "familirization": "Очная", "avgm": 0.0, "institute": "ИРИТ-РТФ", "compensation": "контрактная основа", "status": "К зачислению", "marks": {"ОМА": {"mark": 50, "case": "КТ"}, "ИСиТ": {"mark": 82, "case": "КТ"}, "РЯ": {"mark": 64, "case": "КТ"}}}, {"total_mark": 211, "edu_doc_original": true, "achievs": 0, "status_epgu": "", "competition": "Основные места", "program": "Прикладная информатика", "priority": 4, "speciality": "09.03.03 Прикладная информатика", "is_without_tests": false, "familirization": "Очно-заочная", "avgm": 0.0, "institute": "ИРИТ-РТФ", "compensation": "контрактная основа", "status": "К зачислению", "marks": {"ОМА": {"mark": 50, "case": "КТ"}, "ИСиТ": {"mark": 82, "case": "КТ"}, "РЯ": {"mark": 64, "case": "КТ"}}}, {"total_mark": 211, "edu_doc_original": true, "achievs": 0, "status_epgu": "", "competition": "Основные места", "program": "Информатика и вычислительная техника", "priority": 6, "speciality": "09.03.01 Информатика и вычислительная техника", "is_without_tests": false, "familirization": "Заочная", "avgm": 0.0, "institute": "ИРИТ-РТФ", "compensation": "контрактная основа", "status": "К зачислению", "marks": {"ОМА": {"mark": 50, "case": "КТ"}, "ИСиТ": {"mark": 82, "case": "КТ"}, "РЯ": {"mark": 64, "case": "КТ"}}}, {"total_mark": 211, "edu_doc_original": true, "achievs": 0, "status_epgu": "", "competition": "Основные места", "program": "Безопасность компьютерных систем", "priority": 1, "speciality": "10.03.01 Информационная безопасность", "is_without_tests": false, "familirization": "Очная", "avgm": 0.0, "institute": "ИРИТ-РТФ", "compensation": "бюджетная основа", "status": "К зачислению", "marks": {"ОМА": {"mark": 50, "case": "КТ"}, "ИСиТ": {"mark": 82, "case": "КТ"}, "РЯ": {"mark": 64, "case": "КТ"}}}, {"total_mark": 211, "edu_doc_original": true, "achievs": 0, "status_epgu": "", "competition": "Основные места", "program": "Информационные системы и технологии", "priority": 2, "speciality": "09.03.02 Информационные системы и технологии", "is_without_tests": false, "familirization": "Очная", "avgm": 0.0, "institute": "ИНМТ", "compensation": "бюджетная основа", "status": "К зачислению", "marks": {"ОМА": {"mark": 50, "case": "КТ"}, "ИСиТ": {"mark": 82, "case": "КТ"}, "РЯ": {"mark": 64, "case": "КТ"}}}, {"total_mark": 211, "edu_doc_original": true, "achievs": 0, "status_epgu": "", "competition": "Основные места", "program": "Прикладная информатика", "priority": 3, "speciality": "09.03.03 Прикладная информатика", "is_without_tests": false, "familirization": "Очная", "avgm": 0.0, "institute": "ИРИТ-РТФ", "compensation": "бюджетная основа", "status": "К зачислению", "marks": {"ОМА": {"mark": 50, "case": "КТ"}, "ИСиТ": {"mark": 82, "case": "КТ"}, "РЯ": {"mark": 64, "case": "КТ"}}}, {"total_mark": 211, "edu_doc_original": true, "achievs": 0, "status_epgu": "", "competition": "Основные места", "program": "Информатика и вычислительная техника", "priority": 4, "speciality": "09.03.01 Информатика и вычислительная техника", "is_without_tests": false, "familirization": "Очная", "avgm": 0.0, "institute": "ИРИТ-РТФ", "compensation": "бюджетная основа", "status": "К зачислению", "marks": {"ОМА": {"mark": 50, "case": "КТ"}, "ИСиТ": {"mark": 82, "case": "КТ"}, "РЯ": {"mark": 64, "case": "КТ"}}}, {"total_mark": 211, "edu_doc_original": true, "achievs": 0, "status_epgu": "", "competition": "Основные места", "program": "Алгоритмы искусственного интеллекта", "priority": 5, "speciality": "09.03.01 Информатика и вычислительная техника", "is_without_tests": false, "familirization": "Очная", "avgm": 0.0, "institute": "ИРИТ-РТФ", "compensation": "бюджетная основа", "status": "К зачислению", "marks": {"ОМА": {"mark": 50, "case": "КТ"}, "ИСиТ": {"mark": 82, "case": "КТ"}, "РЯ": {"mark": 64, "case": "КТ"}}}]}, {"_id": "6580b3e31ebc4f1b43752bae", "regnum": 261461, "snils": "17872558931", "applications": [{"total_mark": 213, "edu_doc_original": false, "achievs": 5, "status_epgu": "", "competition": "Основные места", "program": "Программная инженерия", "priority": 1, "speciality": "09.03.04 Программная инженерия", "is_without_tests": false, "familirization": "Очная", "avgm": 0.0, "institute": "ИРИТ-РТФ", "compensation": "контрактная основа", "status": "Зачислен", "marks": {"Ф": {"mark": 47, "case": "ЕГЭ"}, "М": {"mark": 70, "case": "ЕГЭ"}, "РЯ": {"mark": 91, "case": "ЕГЭ"}}}]}, {"_id": "6580b3e31ebc4f1b43752bb8", "regnum": 261471, "snils": "19935630927", "applications": [{"total_mark": 230, "edu_doc_original": true, "achievs": 0, "status_epgu": "", "competition": "Основные места", "program": "Прикладная информатика", "priority": 1, "speciality": "09.03.03 Прикладная информатика", "is_without_tests": false, "familirization": "Очно-заочная", "avgm": 0.0, "institute": "ИРИТ-РТФ", "compensation": "контрактная основа", "status": "К зачислению", "marks": {"ОМА": {"mark": 50, "case": "КТ"}, "ИСиТ": {"mark": 96, "case": "КТ"}, "РЯ": {"mark": 84, "case": "КТ"}}}, {"total_mark": 230, "edu_doc_original": true, "achievs": 0, "status_epgu": "", "competition": "Основные места", "program": "Прикладная информатика", "priority": 1, "speciality": "09.03.03 Прикладная информатика", "is_without_tests": false, "familirization": "Очная", "avgm": 0.0, "institute": "ИРИТ-РТФ", "compensation": "бюджетная основа", "status": "К зачислению", "marks": {"ОМА": {"mark": 50, "case": "КТ"}, "ИСиТ": {"mark": 96, "case": "КТ"}, "РЯ": {"mark": 84, "case": "КТ"}}}, {"total_mark": 230, "edu_doc_original": true, "achievs": 0, "status_epgu": "", "competition": "Основные места", "program": "Алгоритмы искусственного интеллекта", "priority": 2, "speciality": "09.03.01 Информатика и вычислительная техника", "is_without_tests": false, "familirization": "Очная", "avgm": 0.0, "institute": "ИРИТ-РТФ", "compensation": "бюджетная основа", "status": "К зачислению", "marks": {"ОМА": {"mark": 50, "case": "КТ"}, "ИСиТ": {"mark": 96, "case": "КТ"}, "РЯ": {"mark": 84, "case": "КТ"}}}]}, {"_id": "6580b3e31ebc4f1b43752be4", "regnum": 261515, "snils": "19916744834", "applications": [{"total_mark": 205, "edu_doc_original": true, "achievs": 0, "status_epgu": "", "competition": "Основные места", "program": "Технология полиграфического и упаковочного производства", "priority": 1, "speciality": "29.03.03 Технология полиграфического и упаковочного производства", "is_without_tests": false, "familirization": "Очная", "avgm": 0.0, "institute": "ИРИТ-РТФ", "compensation": "бюджетная основа", "status": "К зачислению", "marks": {"ИнжГ": {"mark": 54, "case": "КТ"}, "ИСиТ": {"mark": 69, "case": "КТ"}, "РЯ": {"mark": 67, "case": "КТ"}}}, {"total_mark": 205, "edu_doc_original": true, "achievs": 0, "status_epgu": "", "competition": "Основные места", "program": "Управление в технических системах", "priority": 2, "speciality": "27.03.04 Управление в технических системах", "is_without_tests": false, "familirization": "Очная", "avgm": 0.0, "institute": "ИРИТ-РТФ", "compensation": "бюджетная основа", "status": "К зачислению", "marks": {"ИнжГ": {"mark": 54, "case": "КТ"}, "ИСиТ": {"mark": 69, "case": "КТ"}, "РЯ": {"mark": 67, "case": "КТ"}}}, {"total_mark": 205, "edu_doc_original": true, "achievs": 0, "status_epgu": "", "competition": "Основные места", "program": "Лазерные, аддитивные и упрочняющие технологии в машиностроении", "priority": 5, "speciality": "12.03.05 Лазерная техника и лазерные технологии", "is_without_tests": false, "familirization": "Очная", "avgm": 0.0, "institute": "ИНМТ", "compensation": "бюджетная основа", "status": "К зачислению", "marks": {"ИнжГ": {"mark": 54, "case": "КТ"}, "ИСиТ": {"mark": 69, "case": "КТ"}, "РЯ": {"mark": 67, "case": "КТ"}}}, {"total_mark": 205, "edu_doc_original": true, "achievs": 0, "status_epgu": "", "competition": "Основные места", "program": "Приборостроение", "priority": 3, "speciality": "12.03.01 Приборостроение", "is_without_tests": false, "familirization": "Очная", "avgm": 0.0, "institute": "ФтИ", "compensation": "бюджетная основа", "status": "К зачислению", "marks": {"ИнжГ": {"mark": 54, "case": "КТ"}, "ИСиТ": {"mark": 69, "case": "КТ"}, "РЯ": {"mark": 67, "case": "КТ"}}}, {"total_mark": 205, "edu_doc_original": true, "achievs": 0, "status_epgu": "", "competition": "Основные места", "program": "Оптические технологии и материалы", "priority": 4, "speciality": "12.03.02 Оптотехника", "is_without_tests": false, "familirization": "Очная", "avgm": 0.0, "institute": "ИНМТ", "compensation": "бюджетная основа", "status": "К зачислению", "marks": {"ИнжГ": {"mark": 54, "case": "КТ"}, "ИСиТ": {"mark": 69, "case": "КТ"}, "РЯ": {"mark": 67, "case": "КТ"}}}]}, {"_id": "6580b3e31ebc4f1b43752bea", "regnum": 261521, "snils": "19502745883", "applications": [{"total_mark": 234, "edu_doc_original": false, "achievs": 0, "status_epgu": "", "competition": "Основные места", "program": "Строительство уникальных зданий и сооружений", "priority": 1, "speciality": "08.05.01 Строительство уникальных зданий и сооружений", "is_without_tests": false, "familirization": "Очная", "avgm": 0.0, "institute": "ИСА", "compensation": "бюджетная основа", "status": "Рейтинг", "marks": {"Ф": {"mark": 64, "case": "ЕГЭ"}, "М": {"mark": 76, "case": "ЕГЭ"}, "РЯ": {"mark": 94, "case": "ЕГЭ"}}}, {"total_mark": 234, "edu_doc_original": false, "achievs": 0, "status_epgu": "", "competition": "Основные места", "program": "Строительство зданий, сооружений и развитие территорий", "priority": 2, "speciality": "08.03.01 Строительство", "is_without_tests": false, "familirization": "Очная", "avgm": 0.0, "institute": "ИСА", "compensation": "бюджетная основа", "status": "Рейтинг", "marks": {"Ф": {"mark": 64, "case": "ЕГЭ"}, "М": {"mark": 76, "case": "ЕГЭ"}, "РЯ": {"mark": 94, "case": "ЕГЭ"}}}, {"total_mark": 257, "edu_doc_original": false, "achievs": 0, "status_epgu": "", "competition": "Основные места", "program": "Бизнес-информатика", "priority": 5, "speciality": "38.03.05 Бизнес-информатика", "is_without_tests": false, "familirization": "Очная", "avgm": 0.0, "institute": "ИнЭУ", "compensation": "бюджетная основа", "status": "Рейтинг", "marks": {"М": {"mark": 76, "case": "ЕГЭ"}, "ИнЯ": {"mark": 87, "case": "ЕГЭ"}, "РЯ": {"mark": 94, "case": "ЕГЭ"}}}, {"total_mark": 234, "edu_doc_original": false, "achievs": 0, "status_epgu": "", "competition": "Основные места", "program": "Производство и применение строительных материалов, изделий и конструкций", "priority": 3, "speciality": "08.03.01 Строительство", "is_without_tests": false, "familirization": "Очная", "avgm": 0.0, "institute": "ИНМТ", "compensation": "бюджетная основа", "status": "Рейтинг", "marks": {"Ф": {"mark": 64, "case": "ЕГЭ"}, "М": {"mark": 76, "case": "ЕГЭ"}, "РЯ": {"mark": 94, "case": "ЕГЭ"}}}, {"total_mark": 234, "edu_doc_original": false, "achievs": 0, "status_epgu": "", "competition": "Основные места", "program": "Системный инжиниринг и цифровое проектирование", "priority": 6, "speciality": "15.03.04 Автоматизация технологических процессов и производств", "is_without_tests": false, "familirization": "Очная", "avgm": 0.0, "institute": "УПИШ", "compensation": "бюджетная основа", "status": "Рейтинг", "marks": {"Ф": {"mark": 64, "case": "ЕГЭ"}, "М": {"mark": 76, "case": "ЕГЭ"}, "РЯ": {"mark": 94, "case": "ЕГЭ"}}}, {"total_mark": 234, "edu_doc_original": false, "achievs": 0, "status_epgu": "", "competition": "Основные места", "program": "Автоматизация технологических процессов и производств", "priority": 7, "speciality": "15.03.04 Автоматизация технологических процессов и производств", "is_without_tests": false, "familirization": "Очная", "avgm": 0.0, "institute": "ИНМТ", "compensation": "бюджетная основа", "status": "Рейтинг", "marks": {"Ф": {"mark": 64, "case": "ЕГЭ"}, "М": {"mark": 76, "case": "ЕГЭ"}, "РЯ": {"mark": 94, "case": "ЕГЭ"}}}, {"total_mark": 234, "edu_doc_original": false, "achievs": 0, "status_epgu": "", "competition": "Основные места", "program": "Управление в технических системах", "priority": 4, "speciality": "27.03.04 Управление в технических системах", "is_without_tests": false, "familirization": "Очная", "avgm": 0.0, "institute": "ИРИТ-РТФ", "compensation": "бюджетная основа", "status": "Рейтинг", "marks": {"Ф": {"mark": 64, "case": "ЕГЭ"}, "М": {"mark": 76, "case": "ЕГЭ"}, "РЯ": {"mark": 94, "case": "ЕГЭ"}}}]}, {"_id": "6580b3e31ebc4f1b43752bfa", "regnum": 261537, "snils": "14292529365", "applications": [{"total_mark": 181, "edu_doc_original": true, "achievs": 0, "status_epgu": "", "competition": "Основные места", "program": "Прикладная информатика", "priority": 2, "speciality": "09.03.03 Прикладная информатика", "is_without_tests": false, "familirization": "Очная", "avgm": 0.0, "institute": "ИРИТ-РТФ", "compensation": "контрактная основа", "status": "К зачислению", "marks": {"ОМА": {"mark": 39, "case": "КТ"}, "ИСиТ": {"mark": 78, "case": "КТ"}, "РЯ": {"mark": 64, "case": "КТ"}}}, {"total_mark": 181, "edu_doc_original": true, "achievs": 0, "status_epgu": "", "competition": "Основные места", "program": "Прикладная информатика", "priority": 1, "speciality": "09.03.03 Прикладная информатика", "is_without_tests": false, "familirization": "Очно-заочная", "avgm": 0.0, "institute": "ИРИТ-РТФ", "compensation": "контрактная основа", "status": "К зачислению", "marks": {"ОМА": {"mark": 39, "case": "КТ"}, "ИСиТ": {"mark": 78, "case": "КТ"}, "РЯ": {"mark": 64, "case": "КТ"}}}, {"total_mark": 181, "edu_doc_original": true, "achievs": 0, "status_epgu": "", "competition": "Основные места", "program": "Прикладная информатика", "priority": 1, "speciality": "09.03.03 Прикладная информатика", "is_without_tests": false, "familirization": "Очная", "avgm": 0.0, "institute": "ИРИТ-РТФ", "compensation": "бюджетная основа", "status": "К зачислению", "marks": {"ОМА": {"mark": 39, "case": "КТ"}, "ИСиТ": {"mark": 78, "case": "КТ"}, "РЯ": {"mark": 64, "case": "КТ"}}}]}, {"_id": "6580b3e31ebc4f1b43752bfd", "regnum": 261540, "snils": "", "applications": [{"total_mark": 118, "edu_doc_original": false, "achievs": 0, "status_epgu": "", "competition": "Основные места", "program": "Программная инженерия", "priority": 3, "speciality": "09.03.04 Программная инженерия", "is_without_tests": false, "familirization": "Очная", "avgm": 0.0, "institute": "ИРИТ-РТФ", "compensation": "контрактная основа", "status": "Рейтинг", "marks": {"Ф": {"mark": 39, "case": "КТ"}, "М": {"mark": 39, "case": "КТ"}, "РЯ": {"mark": 40, "case": "КТ"}}}, {"total_mark": 118, "edu_doc_original": false, "achievs": 0, "status_epgu": "", "competition": "Основные места", "program": "Производство и применение строительных материалов, изделий и конструкций", "priority": 2, "speciality": "08.03.01 Строительство", "is_without_tests": false, "familirization": "Очная", "avgm": 0.0, "institute": "ИНМТ", "compensation": "контрактная основа", "status": "Рейтинг", "marks": {"Ф": {"mark": 39, "case": "КТ"}, "М": {"mark": 39, "case": "КТ"}, "РЯ": {"mark": 40, "case": "КТ"}}}, {"total_mark": 118, "edu_doc_original": false, "achievs": 0, "status_epgu": "", "competition": "Основные места", "program": "Прикладная информатика", "priority": 1, "speciality": "09.03.03 Прикладная информатика", "is_without_tests": false, "familirization": "Очная", "avgm": 0.0, "institute": "ИРИТ-РТФ", "compensation": "контрактная основа", "status": "Рейтинг", "marks": {"Ф": {"mark": 39, "case": "КТ"}, "М": {"mark": 39, "case": "КТ"}, "РЯ": {"mark": 40, "case": "КТ"}}}, {"total_mark": 118, "edu_doc_original": false, "achievs": 0, "status_epgu": "", "competition": "Основные места", "program": "Электроника и наноэлектроника", "priority": 4, "speciality": "11.03.04 Электроника и наноэлектроника", "is_without_tests": false, "familirization": "Очная", "avgm": 0.0, "institute": "ФтИ", "compensation": "контрактная основа", "status": "Рейтинг", "marks": {"Ф": {"mark": 39, "case": "КТ"}, "М": {"mark": 39, "case": "КТ"}, "РЯ": {"mark": 40, "case": "КТ"}}}, {"total_mark": 125, "edu_doc_original": false, "achievs": 0, "status_epgu": "", "competition": "Основные места", "program": "Государственное и муниципальное управление", "priority": 5, "speciality": "38.03.04 Государственное и муниципальное управление", "is_without_tests": false, "familirization": "Очная", "avgm": 0.0, "institute": "ИнЭУ", "compensation": "контрактная основа", "status": "Рейтинг", "marks": {"Г": {"mark": 40, "case": "КТ"}, "О": {"mark": 45, "case": "КТ"}, "РЯ": {"mark": 40, "case": "КТ"}}}, {"total_mark": 118, "edu_doc_original": false, "achievs": 0, "status_epgu": "", "competition": "Основные места", "program": "Программная инженерия", "priority": 3, "speciality": "09.03.04 Программная инженерия", "is_without_tests": false, "familirization": "Очная", "avgm": 0.0, "institute": "ИРИТ-РТФ", "compensation": "бюджетная основа", "status": "Рейтинг", "marks": {"Ф": {"mark": 39, "case": "КТ"}, "М": {"mark": 39, "case": "КТ"}, "РЯ": {"mark": 40, "case": "КТ"}}}, {"total_mark": 118, "edu_doc_original": false, "achievs": 0, "status_epgu": "", "competition": "Основные места", "program": "Производство и применение строительных материалов, изделий и конструкций", "priority": 4, "speciality": "08.03.01 Строительство", "is_without_tests": false, "familirization": "Очная", "avgm": 0.0, "institute": "ИНМТ", "compensation": "бюджетная основа", "status": "Рейтинг", "marks": {"Ф": {"mark": 39, "case": "КТ"}, "М": {"mark": 39, "case": "КТ"}, "РЯ": {"mark": 40, "case": "КТ"}}}, {"total_mark": 118, "edu_doc_original": false, "achievs": 0, "status_epgu": "", "competition": "Основные места", "program": "Прикладная информатика", "priority": 5, "speciality": "09.03.03 Прикладная информатика", "is_without_tests": false, "familirization": "Очная", "avgm": 0.0, "institute": "ИРИТ-РТФ", "compensation": "бюджетная основа", "status": "Рейтинг", "marks": {"Ф": {"mark": 39, "case": "КТ"}, "М": {"mark": 39, "case": "КТ"}, "РЯ": {"mark": 40, "case": "КТ"}}}, {"total_mark": 118, "edu_doc_original": false, "achievs": 0, "status_epgu": "", "competition": "Основные места", "program": "Электроника и наноэлектроника", "priority": 2, "speciality": "11.03.04 Электроника и наноэлектроника", "is_without_tests": false, "familirization": "Очная", "avgm": 0.0, "institute": "ФтИ", "compensation": "бюджетная основа", "status": "Рейтинг", "marks": {"Ф": {"mark": 39, "case": "КТ"}, "М": {"mark": 39, "case": "КТ"}, "РЯ": {"mark": 40, "case": "КТ"}}}, {"total_mark": 125, "edu_doc_original": false, "achievs": 0, "status_epgu": "", "competition": "Основные места", "program": "Государственное и муниципальное управление", "priority": 1, "speciality": "38.03.04 Государственное и муниципальное управление", "is_without_tests": false, "familirization": "Очная", "avgm": 0.0, "institute": "ИнЭУ", "compensation": "бюджетная основа", "status": "Рейтинг", "marks": {"Г": {"mark": 40, "case": "КТ"}, "О": {"mark": 45, "case": "КТ"}, "РЯ": {"mark": 40, "case": "КТ"}}}]}, {"_id": "6580b3e31ebc4f1b43752c03", "regnum": 261546, "snils": "19660225284", "applications": [{"total_mark": 243, "edu_doc_original": true, "achievs": 0, "status_epgu": "", "competition": "Основные места", "program": "Безопасность компьютерных систем", "priority": 1, "speciality": "10.03.01 Информационная безопасность", "is_without_tests": false, "familirization": "Очная", "avgm": 0.0, "institute": "ИРИТ-РТФ", "compensation": "бюджетная основа", "status": "К зачислению", "marks": {"ОМА": {"mark": 70, "case": "КТ"}, "ИСиТ": {"mark": 91, "case": "КТ"}, "РЯ": {"mark": 82, "case": "КТ"}}}, {"total_mark": 243, "edu_doc_original": true, "achievs": 0, "status_epgu": "", "competition": "Основные места", "program": "Математические методы защиты информации", "priority": 2, "speciality": "10.05.01 Компьютерная безопасность", "is_without_tests": false, "familirization": "Очная", "avgm": 0.0, "institute": "ИЕНиМ", "compensation": "бюджетная основа", "status": "К зачислению", "marks": {"ОМА": {"mark": 70, "case": "КТ"}, "ИСиТ": {"mark": 91, "case": "КТ"}, "РЯ": {"mark": 82, "case": "КТ"}}}, {"total_mark": 243, "edu_doc_original": true, "achievs": 0, "status_epgu": "", "competition": "Основные места", "program": "Алгоритмы искусственного интеллекта", "priority": 4, "speciality": "09.03.01 Информатика и вычислительная техника", "is_without_tests": false, "familirization": "Очная", "avgm": 0.0, "institute": "ИРИТ-РТФ", "compensation": "бюджетная основа", "status": "К зачислению", "marks": {"ОМА": {"mark": 70, "case": "КТ"}, "ИСиТ": {"mark": 91, "case": "КТ"}, "РЯ": {"mark": 82, "case": "КТ"}}}, {"total_mark": 243, "edu_doc_original": true, "achievs": 0, "status_epgu": "", "competition": "Основные места", "program": "Информационная безопасность телекоммуникационных систем", "priority": 3, "speciality": "10.05.02 Информационная безопасность телекоммуникационных систем", "is_without_tests": false, "familirization": "Очная", "avgm": 0.0, "institute": "ИРИТ-РТФ", "compensation": "бюджетная основа", "status": "К зачислению", "marks": {"ОМА": {"mark": 70, "case": "КТ"}, "ИСиТ": {"mark": 91, "case": "КТ"}, "РЯ": {"mark": 82, "case": "КТ"}}}, {"total_mark": 243, "edu_doc_original": true, "achievs": 0, "status_epgu": "", "competition": "Основные места", "program": "Прикладная информатика", "priority": 5, "speciality": "09.03.03 Прикладная информатика", "is_without_tests": false, "familirization": "Очная", "avgm": 0.0, "institute": "ИРИТ-РТФ", "compensation": "бюджетная основа", "status": "К зачислению", "marks": {"ОМА": {"mark": 70, "case": "КТ"}, "ИСиТ": {"mark": 91, "case": "КТ"}, "РЯ": {"mark": 82, "case": "КТ"}}}]}, {"_id": "6580b3e31ebc4f1b43752c08", "regnum": 261551, "snils": "11774055254", "applications": [{"total_mark": 74, "edu_doc_original": true, "achievs": 0, "status_epgu": "", "competition": "Основные места", "program": "Прикладной анализ данных", "priority": 2, "speciality": "09.04.02 Информационные системы и технологии", "is_without_tests": false, "familirization": "Очная", "avgm": 0.0, "institute": "ИРИТ-РТФ", "compensation": "контрактная основа", "status": "К зачислению", "marks": {"Экзамен 09.04.01;09.04.02": {"mark": 74, "case": "КТ"}}}, {"total_mark": 74, "edu_doc_original": true, "achievs": 0, "status_epgu": "", "competition": "Основные места", "program": "Инженерия искусственного интеллекта", "priority": 1, "speciality": "09.04.01 Информатика и вычислительная техника", "is_without_tests": false, "familirization": "Очная", "avgm": 0.0, "institute": "ИРИТ-РТФ", "compensation": "контрактная основа", "status": "К зачислению", "marks": {"Экзамен 09.04.01;09.04.02": {"mark": 74, "case": "КТ"}}}, {"total_mark": 74, "edu_doc_original": true, "achievs": 0, "status_epgu": "", "competition": "Основные места", "program": "Прикладной анализ данных", "priority": 2, "speciality": "09.04.02 Информационные системы и технологии", "is_without_tests": false, "familirization": "Очная", "avgm": 0.0, "institute": "ИРИТ-РТФ", "compensation": "бюджетная основа", "status": "К зачислению", "marks": {"Экзамен 09.04.01;09.04.02": {"mark": 74, "case": "КТ"}}}, {"total_mark": 74, "edu_doc_original": true, "achievs": 0, "status_epgu": "", "competition": "Основные места", "program": "Инженерия искусственного интеллекта", "priority": 1, "speciality": "09.04.01 Информатика и вычислительная техника", "is_without_tests": false, "familirization": "Очная", "avgm": 0.0, "institute": "ИРИТ-РТФ", "compensation": "бюджетная основа", "status": "К зачислению", "marks": {"Экзамен 09.04.01;09.04.02": {"mark": 74, "case": "КТ"}}}]}, {"_id": "6580b3e31ebc4f1b43752c0b", "regnum": 261554, "snils": "", "applications": [{"total_mark": 55, "edu_doc_original": false, "achievs": 0, "status_epgu": "", "competition": "Основные места", "program": "Прикладной искусственный интеллект / Practical Artificial Intelligence (реализуется полностью на английском языке)", "priority": 1, "speciality": "09.04.02 Информационные системы и технологии", "is_without_tests": false, "familirization": "Очная", "avgm": 0.0, "institute": "ИРИТ-РТФ", "compensation": "контрактная основа", "status": "Рейтинг", "marks": {"Экзамен 09.04.02 (англ.)": {"mark": 55, "case": "Э"}}}]}, {"_id": "6580b3e31ebc4f1b43752c0c", "regnum": 261555, "snils": "15705530152", "applications": [{"total_mark": 183, "edu_doc_original": true, "achievs": 0, "status_epgu": "", "competition": "Основные места", "program": "Математические методы защиты информации", "priority": 1, "speciality": "10.05.01 Компьютерная безопасность", "is_without_tests": false, "familirization": "Очная", "avgm": 0.0, "institute": "ИЕНиМ", "compensation": "контрактная основа", "status": "Зачислен", "marks": {"Ф": {"mark": 52, "case": "ЕГЭ"}, "М": {"mark": 58, "case": "ЕГЭ"}, "РЯ": {"mark": 73, "case": "ЕГЭ"}}}, {"total_mark": 207, "edu_doc_original": true, "achievs": 0, "status_epgu": "", "competition": "Основные места", "program": "Бизнес-информатика", "priority": 2, "speciality": "38.03.05 Бизнес-информатика", "is_without_tests": false, "familirization": "Очная", "avgm": 0.0, "institute": "ИнЭУ", "compensation": "контрактная основа", "status": "К зачислению", "marks": {"М": {"mark": 58, "case": "ЕГЭ"}, "ИнЯ": {"mark": 76, "case": "ЕГЭ"}, "РЯ": {"mark": 73, "case": "ЕГЭ"}}}, {"total_mark": 183, "edu_doc_original": true, "achievs": 0, "status_epgu": "", "competition": "Основные места", "program": "Безопасность компьютерных систем", "priority": 3, "speciality": "10.03.01 Информационная безопасность", "is_without_tests": false, "familirization": "Очная", "avgm": 0.0, "institute": "ИРИТ-РТФ", "compensation": "контрактная основа", "status": "К зачислению", "marks": {"Ф": {"mark": 52, "case": "ЕГЭ"}, "М": {"mark": 58, "case": "ЕГЭ"}, "РЯ": {"mark": 73, "case": "ЕГЭ"}}}, {"total_mark": 183, "edu_doc_original": true, "achievs": 0, "status_epgu": "", "competition": "Основные места", "program": "Информационно-аналитические системы безопасности", "priority": 4, "speciality": "10.05.04 Информационно-аналитические системы безопасности", "is_without_tests": false, "familirization": "Очная", "avgm": 0.0, "institute": "ИРИТ-РТФ", "compensation": "контрактная основа", "status": "К зачислению", "marks": {"Ф": {"mark": 52, "case": "ЕГЭ"}, "М": {"mark": 58, "case": "ЕГЭ"}, "РЯ": {"mark": 73, "case": "ЕГЭ"}}}, {"total_mark": 183, "edu_doc_original": true, "achievs": 0, "status_epgu": "", "competition": "Основные места", "program": "Информационная безопасность телекоммуникационных систем", "priority": 5, "speciality": "10.05.02 Информационная безопасность телекоммуникационных систем", "is_without_tests": false, "familirization": "Очная", "avgm": 0.0, "institute": "ИРИТ-РТФ", "compensation": "контрактная основа", "status": "К зачислению", "marks": {"Ф": {"mark": 52, "case": "ЕГЭ"}, "М": {"mark": 58, "case": "ЕГЭ"}, "РЯ": {"mark": 73, "case": "ЕГЭ"}}}, {"total_mark": 183, "edu_doc_original": true, "achievs": 0, "status_epgu": "", "competition": "Основные места", "program": "Математические методы защиты информации", "priority": 1, "speciality": "10.05.01 Компьютерная безопасность", "is_without_tests": false, "familirization": "Очная", "avgm": 0.0, "institute": "ИЕНиМ", "compensation": "бюджетная основа", "status": "К зачислению", "marks": {"Ф": {"mark": 52, "case": "ЕГЭ"}, "М": {"mark": 58, "case": "ЕГЭ"}, "РЯ": {"mark": 73, "case": "ЕГЭ"}}}, {"total_mark": 207, "edu_doc_original": true, "achievs": 0, "status_epgu": "", "competition": "Основные места", "program": "Бизнес-информатика", "priority": 2, "speciality": "38.03.05 Бизнес-информатика", "is_without_tests": false, "familirization": "Очная", "avgm": 0.0, "institute": "ИнЭУ", "compensation": "бюджетная основа", "status": "К зачислению", "marks": {"М": {"mark": 58, "case": "ЕГЭ"}, "ИнЯ": {"mark": 76, "case": "ЕГЭ"}, "РЯ": {"mark": 73, "case": "ЕГЭ"}}}, {"total_mark": 183, "edu_doc_original": true, "achievs": 0, "status_epgu": "", "competition": "Основные места", "program": "Безопасность компьютерных систем", "priority": 3, "speciality": "10.03.01 Информационная безопасность", "is_without_tests": false, "familirization": "Очная", "avgm": 0.0, "institute": "ИРИТ-РТФ", "compensation": "бюджетная основа", "status": "К зачислению", "marks": {"Ф": {"mark": 52, "case": "ЕГЭ"}, "М": {"mark": 58, "case": "ЕГЭ"}, "РЯ": {"mark": 73, "case": "ЕГЭ"}}}, {"total_mark": 183, "edu_doc_original": true, "achievs": 0, "status_epgu": "", "competition": "Основные места", "program": "Информационно-аналитические системы безопасности", "priority": 4, "speciality": "10.05.04 Информационно-аналитические системы безопасности", "is_without_tests": false, "familirization": "Очная", "avgm": 0.0, "institute": "ИРИТ-РТФ", "compensation": "бюджетная основа", "status": "К зачислению", "marks": {"Ф": {"mark": 52, "case": "ЕГЭ"}, "М": {"mark": 58, "case": "ЕГЭ"}, "РЯ": {"mark": 73, "case": "ЕГЭ"}}}, {"total_mark": 183, "edu_doc_original": true, "achievs": 0, "status_epgu": "", "competition": "Основные места", "program": "Информационная безопасность телекоммуникационных систем", "priority": 5, "speciality": "10.05.02 Информационная безопасность телекоммуникационных систем", "is_without_tests": false, "familirization": "Очная", "avgm": 0.0, "institute": "ИРИТ-РТФ", "compensation": "бюджетная основа", "status": "К зачислению", "marks": {"Ф": {"mark": 52, "case": "ЕГЭ"}, "М": {"mark": 58, "case": "ЕГЭ"}, "РЯ": {"mark": 73, "case": "ЕГЭ"}}}]}, {"_id": "6580b3e31ebc4f1b43752c0e", "regnum": 261557, "snils": "", "applications": [{"total_mark": 90, "edu_doc_original": false, "achievs": 0, "status_epgu": "", "competition": "Основные места", "program": "Прикладной искусственный интеллект / Practical Artificial Intelligence (реализуется полностью на английском языке)", "priority": 1, "speciality": "09.04.02 Информационные системы и технологии", "is_without_tests": false, "familirization": "Очная", "avgm": 0.0, "institute": "ИРИТ-РТФ", "compensation": "контрактная основа", "status": "Рейтинг", "marks": {"Экзамен 09.04.02 (англ.)": {"mark": 90, "case": "Э"}}}]}, {"_id": "6580b3e31ebc4f1b43752c15", "regnum": 261564, "snils": "19118374781", "applications": [{"total_mark": 167, "edu_doc_original": false, "achievs": 0, "status_epgu": "", "competition": "Основные места", "program": "Сервис в индустрии спорта и рекреации", "priority": 4, "speciality": "43.03.01 Сервис", "is_without_tests": false, "familirization": "Очная", "avgm": 0.0, "institute": "ИФКСиМП", "compensation": "бюджетная основа", "status": "Рейтинг", "marks": {"М": {"mark": 39, "case": "ЕГЭ"}, "ИнЯ": {"mark": 55, "case": "ЕГЭ"}, "РЯ": {"mark": 73, "case": "ЕГЭ"}}}, {"total_mark": 167, "edu_doc_original": false, "achievs": 0, "status_epgu": "", "competition": "Основные места", "program": "Сервис в индустрии спорта и рекреации", "priority": 6, "speciality": "43.03.01 Сервис", "is_without_tests": false, "familirization": "Заочная", "avgm": 0.0, "institute": "ИФКСиМП", "compensation": "бюджетная основа", "status": "Рейтинг", "marks": {"М": {"mark": 39, "case": "ЕГЭ"}, "ИнЯ": {"mark": 55, "case": "ЕГЭ"}, "РЯ": {"mark": 73, "case": "ЕГЭ"}}}, {"total_mark": 163, "edu_doc_original": false, "achievs": 0, "status_epgu": "", "competition": "Основные места", "program": "Алгоритмы искусственного интеллекта", "priority": 2, "speciality": "09.03.01 Информатика и вычислительная техника", "is_without_tests": false, "familirization": "Очная", "avgm": 0.0, "institute": "ИРИТ-РТФ", "compensation": "бюджетная основа", "status": "Рейтинг", "marks": {"Инф": {"mark": 51, "case": "ЕГЭ"}, "М": {"mark": 39, "case": "ЕГЭ"}, "РЯ": {"mark": 73, "case": "ЕГЭ"}}}, {"total_mark": 167, "edu_doc_original": false, "achievs": 0, "status_epgu": "", "competition": "Основные места", "program": "Бизнес-информатика", "priority": 3, "speciality": "38.03.05 Бизнес-информатика", "is_without_tests": false, "familirization": "Очная", "avgm": 0.0, "institute": "ИнЭУ", "compensation": "бюджетная основа", "status": "Рейтинг", "marks": {"М": {"mark": 39, "case": "ЕГЭ"}, "ИнЯ": {"mark": 55, "case": "ЕГЭ"}, "РЯ": {"mark": 73, "case": "ЕГЭ"}}}, {"total_mark": 167, "edu_doc_original": false, "achievs": 0, "status_epgu": "", "competition": "Основные места", "program": "Сервис", "priority": 5, "speciality": "43.03.01 Сервис", "is_without_tests": false, "familirization": "Заочная", "avgm": 0.0, "institute": "УГИ", "compensation": "бюджетная основа", "status": "Рейтинг", "marks": {"М": {"mark": 39, "case": "ЕГЭ"}, "ИнЯ": {"mark": 55, "case": "ЕГЭ"}, "РЯ": {"mark": 73, "case": "ЕГЭ"}}}, {"total_mark": 167, "edu_doc_original": false, "achievs": 0, "status_epgu": "", "competition": "Основные места", "program": "Сервис", "priority": 1, "speciality": "43.03.01 Сервис", "is_without_tests": false, "familirization": "Очная", "avgm": 0.0, "institute": "УГИ", "compensation": "бюджетная основа", "status": "Рейтинг", "marks": {"М": {"mark": 39, "case": "ЕГЭ"}, "ИнЯ": {"mark": 55, "case": "ЕГЭ"}, "РЯ": {"mark": 73, "case": "ЕГЭ"}}}]}, {"_id": "6580b3e31ebc4f1b43752c2c", "regnum": 261587, "snils": "00674563653", "applications": [{"total_mark": 88, "edu_doc_original": false, "achievs": 10, "status_epgu": "", "competition": "Основные места", "program": "Инженерия машинного обучения", "priority": 1, "speciality": "09.04.01 Информатика и вычислительная техника", "is_without_tests": false, "familirization": "Очная", "avgm": 0.0, "institute": "ИРИТ-РТФ", "compensation": "контрактная основа", "status": "Рейтинг", "marks": {"Экзамен 09.04.01;09.04.02": {"mark": 78, "case": "КТ"}}}]}, {"_id": "6580b3e31ebc4f1b43752c2d", "regnum": 261588, "snils": "", "applications": [{"total_mark": 262, "edu_doc_original": true, "achievs": 0, "status_epgu": "", "competition": "Основные места", "program": "Прикладная информатика", "priority": 2, "speciality": "09.03.03 Прикладная информатика", "is_without_tests": false, "familirization": "Очная", "avgm": 0.0, "institute": "ИРИТ-РТФ", "compensation": "бюджетная основа", "status": "Отклонено", "marks": {"Ф": {"mark": 100, "case": "КТ"}, "М": {"mark": 78, "case": "КТ"}, "РЯ": {"mark": 84, "case": "КТ"}}}, {"total_mark": 262, "edu_doc_original": true, "achievs": 0, "status_epgu": "", "competition": "Основные места", "program": "Информатика и вычислительная техника", "priority": 3, "speciality": "09.03.01 Информатика и вычислительная техника", "is_without_tests": false, "familirization": "Очная", "avgm": 0.0, "institute": "ИРИТ-РТФ", "compensation": "бюджетная основа", "status": "Отклонено", "marks": {"Ф": {"mark": 100, "case": "КТ"}, "М": {"mark": 78, "case": "КТ"}, "РЯ": {"mark": 84, "case": "КТ"}}}, {"total_mark": 262, "edu_doc_original": true, "achievs": 0, "status_epgu": "", "competition": "Основные места", "program": "Алгоритмы искусственного интеллекта", "priority": 4, "speciality": "09.03.01 Информатика и вычислительная техника", "is_without_tests": false, "familirization": "Очная", "avgm": 0.0, "institute": "ИРИТ-РТФ", "compensation": "бюджетная основа", "status": "Отклонено", "marks": {"Ф": {"mark": 100, "case": "КТ"}, "М": {"mark": 78, "case": "КТ"}, "РЯ": {"mark": 84, "case": "КТ"}}}]}, {"_id": "6580b3e31ebc4f1b43752c2e", "regnum": 261589, "snils": "19299695457", "applications": [{"total_mark": 246, "edu_doc_original": true, "achievs": 5, "status_epgu": "", "competition": "Основные места", "program": "Прикладная информатика", "priority": 1, "speciality": "09.03.03 Прикладная информатика", "is_without_tests": false, "familirization": "Очная", "avgm": 0.0, "institute": "ИРИТ-РТФ", "compensation": "бюджетная основа", "status": "К зачислению", "marks": {"Инф": {"mark": 83, "case": "ЕГЭ"}, "М": {"mark": 76, "case": "ЕГЭ"}, "РЯ": {"mark": 82, "case": "ЕГЭ"}}}, {"total_mark": 246, "edu_doc_original": true, "achievs": 5, "status_epgu": "", "competition": "Основные места", "program": "Программная инженерия", "priority": 3, "speciality": "09.03.04 Программная инженерия", "is_without_tests": false, "familirization": "Очная", "avgm": 0.0, "institute": "ИРИТ-РТФ", "compensation": "бюджетная основа", "status": "К зачислению", "marks": {"Инф": {"mark": 83, "case": "ЕГЭ"}, "М": {"mark": 76, "case": "ЕГЭ"}, "РЯ": {"mark": 82, "case": "ЕГЭ"}}}, {"total_mark": 246, "edu_doc_original": true, "achievs": 5, "status_epgu": "", "competition": "Основные места", "program": "Информатика и вычислительная техника", "priority": 2, "speciality": "09.03.01 Информатика и вычислительная техника", "is_without_tests": false, "familirization": "Очная", "avgm": 0.0, "institute": "ИРИТ-РТФ", "compensation": "бюджетная основа", "status": "К зачислению", "marks": {"Инф": {"mark": 83, "case": "ЕГЭ"}, "М": {"mark": 76, "case": "ЕГЭ"}, "РЯ": {"mark": 82, "case": "ЕГЭ"}}}, {"total_mark": 246, "edu_doc_original": true, "achievs": 5, "status_epgu": "", "competition": "Основные места", "program": "Технология полиграфического и упаковочного производства", "priority": 4, "speciality": "29.03.03 Технология полиграфического и упаковочного производства", "is_without_tests": false, "familirization": "Очная", "avgm": 0.0, "institute": "ИРИТ-РТФ", "compensation": "бюджетная основа", "status": "К зачислению", "marks": {"Инф": {"mark": 83, "case": "ЕГЭ"}, "М": {"mark": 76, "case": "ЕГЭ"}, "РЯ": {"mark": 82, "case": "ЕГЭ"}}}]}, {"_id": "6580b3e31ebc4f1b43752c40", "regnum": 261607, "snils": "09987948585", "applications": [{"total_mark": 73, "edu_doc_original": true, "achievs": 0, "status_epgu": "", "competition": "Основные места", "program": "Инженерия радиоэлектронных средств и систем", "priority": 1, "speciality": "11.04.01 Радиотехника", "is_without_tests": false, "familirization": "Очная", "avgm": 0.0, "institute": "ИРИТ-РТФ", "compensation": "бюджетная основа", "status": "К зачислению", "marks": {"Экзамен 09.04.01;09.04.02": {"mark": 73, "case": "КТ"}}}, {"total_mark": 71, "edu_doc_original": true, "achievs": 0, "status_epgu": "", "competition": "Основные места", "program": "Приборы и методы контроля качества и диагностики", "priority": 2, "speciality": "12.04.01 Приборостроение", "is_without_tests": false, "familirization": "Очная", "avgm": 0.0, "institute": "ФтИ", "compensation": "бюджетная основа", "status": "К зачислению", "marks": {"Экзамен 11.04.04;12.04.01": {"mark": 71, "case": "КТ"}}}]}, {"_id": "6580b3e31ebc4f1b43752c4c", "regnum": 261619, "snils": "16415242443", "applications": [{"total_mark": 148, "edu_doc_original": true, "achievs": 0, "status_epgu": "", "competition": "Основные места", "program": "Электроэнергетика и электротехника", "priority": 1, "speciality": "13.03.02 Электроэнергетика и электротехника", "is_without_tests": false, "familirization": "Очная", "avgm": 0.0, "institute": "УралЭНИН", "compensation": "контрактная основа", "status": "К зачислению", "marks": {"Ф": {"mark": 41, "case": "ЕГЭ"}, "М": {"mark": 46, "case": "ЕГЭ"}, "РЯ": {"mark": 61, "case": "ЕГЭ"}}}, {"total_mark": 148, "edu_doc_original": true, "achievs": 0, "status_epgu": "", "competition": "Основные места", "program": "Информатика и вычислительная техника", "priority": 2, "speciality": "09.03.01 Информатика и вычислительная техника", "is_without_tests": false, "familirization": "Очная", "avgm": 0.0, "institute": "ИРИТ-РТФ", "compensation": "контрактная основа", "status": "К зачислению", "marks": {"Ф": {"mark": 41, "case": "ЕГЭ"}, "М": {"mark": 46, "case": "ЕГЭ"}, "РЯ": {"mark": 61, "case": "ЕГЭ"}}}, {"total_mark": 148, "edu_doc_original": true, "achievs": 0, "status_epgu": "", "competition": "Основные места", "program": "Прикладная информатика", "priority": 3, "speciality": "09.03.03 Прикладная информатика", "is_without_tests": false, "familirization": "Очная", "avgm": 0.0, "institute": "ИРИТ-РТФ", "compensation": "контрактная основа", "status": "К зачислению", "marks": {"Ф": {"mark": 41, "case": "ЕГЭ"}, "М": {"mark": 46, "case": "ЕГЭ"}, "РЯ": {"mark": 61, "case": "ЕГЭ"}}}, {"total_mark": 148, "edu_doc_original": true, "achievs": 0, "status_epgu": "", "competition": "Основные места", "program": "Электроэнергетика и электротехника", "priority": 1, "speciality": "13.03.02 Электроэнергетика и электротехника", "is_without_tests": false, "familirization": "Очная", "avgm": 0.0, "institute": "УралЭНИН", "compensation": "бюджетная основа", "status": "К зачислению", "marks": {"Ф": {"mark": 41, "case": "ЕГЭ"}, "М": {"mark": 46, "case": "ЕГЭ"}, "РЯ": {"mark": 61, "case": "ЕГЭ"}}}, {"total_mark": 148, "edu_doc_original": true, "achievs": 0, "status_epgu": "", "competition": "Основные места", "program": "Информатика и вычислительная техника", "priority": 2, "speciality": "09.03.01 Информатика и вычислительная техника", "is_without_tests": false, "familirization": "Очная", "avgm": 0.0, "institute": "ИРИТ-РТФ", "compensation": "бюджетная основа", "status": "К зачислению", "marks": {"Ф": {"mark": 41, "case": "ЕГЭ"}, "М": {"mark": 46, "case": "ЕГЭ"}, "РЯ": {"mark": 61, "case": "ЕГЭ"}}}, {"total_mark": 148, "edu_doc_original": true, "achievs": 0, "status_epgu": "", "competition": "Основные места", "program": "Прикладная информатика", "priority": 3, "speciality": "09.03.03 Прикладная информатика", "is_without_tests": false, "familirization": "Очная", "avgm": 0.0, "institute": "ИРИТ-РТФ", "compensation": "бюджетная основа", "status": "К зачислению", "marks": {"Ф": {"mark": 41, "case": "ЕГЭ"}, "М": {"mark": 46, "case": "ЕГЭ"}, "РЯ": {"mark": 61, "case": "ЕГЭ"}}}]}, {"_id": "6580b3e31ebc4f1b43752c53", "regnum": 261626, "snils": "03114973524", "applications": [{"total_mark": 78, "edu_doc_original": false, "achievs": 0, "status_epgu": "", "competition": "Основные места", "program": "Инженерия машинного обучения", "priority": 1, "speciality": "09.04.01 Информатика и вычислительная техника", "is_without_tests": false, "familirization": "Очная", "avgm": 0.0, "institute": "ИРИТ-РТФ", "compensation": "контрактная основа", "status": "Рейтинг", "marks": {"Экзамен 09.04.01;09.04.02": {"mark": 78, "case": "КТ"}}}]}]